lascli/__init__.py
lascli/__main__.py
lascli/__version__.py
lascli/util.py
lascli/actions/workflows.py
lascli/parser/__init__.py
lascli/parser/app_clients.py
lascli/parser/assets.py
lascli/parser/datasets.py
lascli/parser/deployment_environments.py
lascli/parser/documents.py
lascli/parser/logs.py
lascli/parser/models.py
lascli/parser/organizations.py
lascli/parser/payment_methods.py
lascli/parser/plans.py
lascli/parser/predictions.py
lascli/parser/roles.py
lascli/parser/secrets.py
lascli/parser/transitions.py
lascli/parser/users.py
lascli/parser/workflows.py
lucidtech_las_cli-13.3.0.dist-info/LICENSE.md
lucidtech_las_cli-13.3.0.dist-info/METADATA
lucidtech_las_cli-13.3.0.dist-info/WHEEL
lucidtech_las_cli-13.3.0.dist-info/entry_points.txt
lucidtech_las_cli-13.3.0.dist-info/top_level.txt
lucidtech_las_cli-13.3.0.dist-info/RECORD
