Metadata-Version: 2.1
Name: lucidtech-las-cli
Version: 13.3.0
Summary: CLI for Lucidtech AI Services
Home-page: https://github.com/LucidtechAI/las-cli
Author: Lucidtech
Author-email: hello@lucidtech.ai
Maintainer: Magnus Aarskaug Rud
Maintainer-email: magnus@lucidtech.ai
License: Apache 2.0
Platform: Posix; MacOS X; Windows
Classifier: Development Status :: 5 - Production/Stable
Classifier: Intended Audience :: Developers
Classifier: License :: OSI Approved :: Apache Software License
Classifier: Operating System :: OS Independent
Classifier: Programming Language :: Python :: 3.8
Classifier: Programming Language :: Python :: 3.9
Classifier: Programming Language :: Python :: 3.10
Classifier: Programming Language :: Python :: 3.11
Classifier: Topic :: Internet
License-File: LICENSE.md
Requires-Dist: PyYAML>=6.0.0
Requires-Dist: argcomplete>=2.0.0
Requires-Dist: dateparser>=1.1.1
Requires-Dist: filetype>=1.0.13
Requires-Dist: lucidtech-las~=11.4
